<?xml version="1.0" encoding="UTF-8"?>
<!DOCTYPE mapper PUBLIC "-//mybatis.org//DTD Mapper 3.0//EN" "http://mybatis.org/dtd/mybatis-3-mapper.dtd">

<mapper namespace="kh.ddeonabom.reply.model.mapper.ReplyMapper">

	<!-- 댓글 목록: POST_NO + POST_BOARD 기준, 등록 오래된 순 -->
	<select id="getReplyList" parameterType="hashmap" resultType="Reply">
		SELECT r.*, m.nickname AS writer
		FROM reply r
		JOIN member m ON r.member_no = m.member_no
		WHERE r.post_no    = #{postNo}
		AND   r.post_board = #{postBoard}
		AND   r.status     = 'Y'
		ORDER BY r.create_date ASC
	</select>

	<!-- 댓글 등록 -->
	<insert id="insertReply" parameterType="Reply">
		INSERT INTO reply (reply_no, content, create_date, status, post_board, post_no, member_no)
		VALUES (SEQ_RNO.NEXTVAL, #{content}, SYSDATE, 'Y', #{postBoard}, #{postNo}, #{memberNo})
	</insert>

	<!-- 댓글 수정 -->
	<update id="updateReply" parameterType="Reply">
		UPDATE reply
		SET content     = #{content},
		    modify_date = SYSDATE
		WHERE reply_no  = #{replyNo}
		AND   member_no = #{memberNo}
		AND   status    = 'Y'
	</update>

	<!-- 댓글 삭제 (soft delete) -->
	<update id="deleteReply" parameterType="hashmap">
		UPDATE reply
		SET status = 'N'
		WHERE reply_no  = #{replyNo}
		AND   member_no = #{memberNo}
	</update>
	<select id="getMyCommentCount" parameterType="hashmap" resultType="_int">
		SELECT COUNT(*)
		FROM reply
		WHERE member_no = #{memberNo}
		  AND post_board = #{postBoard} AND status = 'Y'
	</select>

	<select id="selectMyCommentList" parameterType="hashmap" resultType="Reply">

		SELECT *
		FROM (
			SELECT r.*, ROW_NUMBER() OVER (ORDER BY r.create_date DESC) AS rnum
			FROM reply r
			WHERE r.member_no = #{memberNo}
			  AND r.post_board = #{postBoard} AND r.status = 'Y'
		)
		WHERE rnum BETWEEN #{startRow} + 1 AND #{startRow} + #{listLimit}
	</select>
	
	

</mapper>
